[
{"soura_nu":"82","ref_number" : "75714","word_w_tashkeel" : "إِذَا","kalemah_tafseer" : "ظَرْفٌ يَدُلُّ في أكْثَرِ الحالاتِ عَلى الزَّمَنِ المُستَقْبَلِ","sorah_name" : "الإنفطار","ayah_number" : "1","kalemah_root" : "إذا","kalemah_no_tashkeel" : "إذا","kalemah_num_in_ayah" : "1","kalemat_count_in_ayah" : "3"},
{"soura_nu":"82","ref_number" : "75715","word_w_tashkeel" : "السَّمَاء","kalemah_tafseer" : "المُرادُ السَّماءُ الكَوْكَبُ","sorah_name" : "الإنفطار","ayah_number" : "1","kalemah_root" : "سمو","kalemah_no_tashkeel" : "السماء","kalemah_num_in_ayah" : "2","kalemat_count_in_ayah" : "3"},
{"soura_nu":"82","ref_number" : "75716","word_w_tashkeel" : "انفَطَرَتْ","kalemah_tafseer" : "انْشَقَّت عند قِـيَـام الساعة","sorah_name" : "الإنفطار","ayah_number" : "1","kalemah_root" : "فطر","kalemah_no_tashkeel" : "انفطرت","kalemah_num_in_ayah" : "3","kalemat_count_in_ayah" : "3"},
{"soura_nu":"82","ref_number" : "75717","word_w_tashkeel" : "وَإِذَا","kalemah_tafseer" : "إذا: ظَرْفُ زَمانٍ يَتَضَمَّنُ مَعْنَى المُفاجَأةِ","sorah_name" : "الإنفطار","ayah_number" : "2","kalemah_root" : "إذا","kalemah_no_tashkeel" : "وإذا","kalemah_num_in_ayah" : "1","kalemat_count_in_ayah" : "3"},
{"soura_nu":"82","ref_number" : "75718","word_w_tashkeel" : "الْكَوَاكِبُ","kalemah_tafseer" : "النجومُ","sorah_name" : "الإنفطار","ayah_number" : "2","kalemah_root" : "كبب","kalemah_no_tashkeel" : "الكواكب","kalemah_num_in_ayah" : "2","kalemat_count_in_ayah" : "3"},
{"soura_nu":"82","ref_number" : "75719","word_w_tashkeel" : "انتَثَرَتْ","kalemah_tafseer" : "تساقطت وتفرقت عند قِـيَـام الساعة","sorah_name" : "الإنفطار","ayah_number" : "2","kalemah_root" : "نثر","kalemah_no_tashkeel" : "انتثرت","kalemah_num_in_ayah" : "3","kalemat_count_in_ayah" : "3"},
{"soura_nu":"82","ref_number" : "75720","word_w_tashkeel" : "وَإِذَا","kalemah_tafseer" : "إذا: ظَرْفُ زَمانٍ يَتَضَمَّنُ مَعْنَى المُفاجَأةِ","sorah_name" : "الإنفطار","ayah_number" : "3","kalemah_root" : "إذا","kalemah_no_tashkeel" : "وإذا","kalemah_num_in_ayah" : "1","kalemat_count_in_ayah" : "3"},
{"soura_nu":"82","ref_number" : "75721","word_w_tashkeel" : "الْبِحَارُ","kalemah_tafseer" : "جَمْعُ بَحْرٍ، والبَحْرُ: مَكانٌ واسِعٌ جامِعٌ للماءِ الكثيرِ","sorah_name" : "الإنفطار","ayah_number" : "3","kalemah_root" : "بحر","kalemah_no_tashkeel" : "البحار","kalemah_num_in_ayah" : "2","kalemat_count_in_ayah" : "3"},
{"soura_nu":"82","ref_number" : "75722","word_w_tashkeel" : "فُجِّرَتْ","kalemah_tafseer" : "تفجَّرت كتفجّر البراكين أو فُجِّرَ بعضها في بعض وشُقَّت جَوانِبهَا فصارت بحرا واحدا وذلك عند قِـيَـام الساعة","sorah_name" : "الإنفطار","ayah_number" : "3","kalemah_root" : "فجر","kalemah_no_tashkeel" : "فجرت","kalemah_num_in_ayah" : "3","kalemat_count_in_ayah" : "3"},
{"soura_nu":"82","ref_number" : "75723","word_w_tashkeel" : "وَإِذَا","kalemah_tafseer" : "إذا: ظَرْفُ زَمانٍ يَتَضَمَّنُ مَعْنَى المُفاجَأةِ","sorah_name" : "الإنفطار","ayah_number" : "4","kalemah_root" : "إذا","kalemah_no_tashkeel" : "وإذا","kalemah_num_in_ayah" : "1","kalemat_count_in_ayah" : "3"},
{"soura_nu":"82","ref_number" : "75724","word_w_tashkeel" : "الْقُبُورُ","kalemah_tafseer" : "جمع قبر، وقَبْر الإنسان: موضع دفنه","sorah_name" : "الإنفطار","ayah_number" : "4","kalemah_root" : "قبر","kalemah_no_tashkeel" : "القبور","kalemah_num_in_ayah" : "2","kalemat_count_in_ayah" : "3"},
{"soura_nu":"82","ref_number" : "75725","word_w_tashkeel" : "بُعْثِرَتْ","kalemah_tafseer" : "أُثيرت وقـُـلِبَ ترابُها وأخْــِرج موتاها","sorah_name" : "الإنفطار","ayah_number" : "4","kalemah_root" : "بعثر","kalemah_no_tashkeel" : "بعثرت","kalemah_num_in_ayah" : "3","kalemat_count_in_ayah" : "3"},
{"soura_nu":"82","ref_number" : "75726","word_w_tashkeel" : "عَلِمَتْ","kalemah_tafseer" : "عرفت وأدركت","sorah_name" : "الإنفطار","ayah_number" : "5","kalemah_root" : "علم","kalemah_no_tashkeel" : "علمت","kalemah_num_in_ayah" : "1","kalemat_count_in_ayah" : "5"},
{"soura_nu":"82","ref_number" : "75727","word_w_tashkeel" : "نَفْسٌ","kalemah_tafseer" : "النفس : الذات أي الروح والجسم معا","sorah_name" : "الإنفطار","ayah_number" : "5","kalemah_root" : "نفس","kalemah_no_tashkeel" : "نفس","kalemah_num_in_ayah" : "2","kalemat_count_in_ayah" : "5"},
{"soura_nu":"82","ref_number" : "75728","word_w_tashkeel" : "مَّا","kalemah_tafseer" : "يُحتَمَلُ أن تكونَ موصولَةً أو مَوْصوفَةً","sorah_name" : "الإنفطار","ayah_number" : "5","kalemah_root" : "ما","kalemah_no_tashkeel" : "ما","kalemah_num_in_ayah" : "3","kalemat_count_in_ayah" : "5"},
{"soura_nu":"82","ref_number" : "75729","word_w_tashkeel" : "قَدَّمَتْ","kalemah_tafseer" : "ما قَدَّمَتْ: ما فَعَلتْ في الدنيا من أعْمالٍ","sorah_name" : "الإنفطار","ayah_number" : "5","kalemah_root" : "قدم","kalemah_no_tashkeel" : "قدمت","kalemah_num_in_ayah" : "4","kalemat_count_in_ayah" : "5"},
{"soura_nu":"82","ref_number" : "75730","word_w_tashkeel" : "وَأَخَّرَتْ","kalemah_tafseer" : "أَخَّرَتْ: تركت عملاً خيراً كان أو شراً ، أو سنَّتْ سنّه حسنة أو سيئة يُعْمَل بها بعدها","sorah_name" : "الإنفطار","ayah_number" : "5","kalemah_root" : "أخر","kalemah_no_tashkeel" : "وأخرت","kalemah_num_in_ayah" : "5","kalemat_count_in_ayah" : "5"},
{"soura_nu":"82","ref_number" : "75731","word_w_tashkeel" : "يَاأَيُّهَا","kalemah_tafseer" : "يَا: لِلنِّداءِ، أَيُّهَا: وَصْلَةٌ لِنِداءِ مَا فيهِ ' ألْ ' مِنَ الذَّكورِ مَع التَّنْبيهِ","sorah_name" : "الإنفطار","ayah_number" : "6","kalemah_root" : "ياأيها","kalemah_no_tashkeel" : "ياأيها","kalemah_num_in_ayah" : "1","kalemat_count_in_ayah" : "6"},
{"soura_nu":"82","ref_number" : "75732","word_w_tashkeel" : "الْإِنسَانُ","kalemah_tafseer" : "الذَّكَر والأنْثَى مِنْ بَنِي آدَمَ","sorah_name" : "الإنفطار","ayah_number" : "6","kalemah_root" : "أنس","kalemah_no_tashkeel" : "الإنسان","kalemah_num_in_ayah" : "2","kalemat_count_in_ayah" : "6"},
{"soura_nu":"82","ref_number" : "75733","word_w_tashkeel" : "مَا","kalemah_tafseer" : "اسمٌ يُسْتَفْهَمُ بِهِ عَنْ غيْرِ العاقِلِ وعَن حَقيقَةِ الشيْءِ أو صِفَتِهِ","sorah_name" : "الإنفطار","ayah_number" : "6","kalemah_root" : "ما","kalemah_no_tashkeel" : "ما","kalemah_num_in_ayah" : "3","kalemat_count_in_ayah" : "6"},
{"soura_nu":"82","ref_number" : "75734","word_w_tashkeel" : "غَرَّكَ","kalemah_tafseer" : "مَا غَرَّكَ بربّك: أيُّ شيء خدعَك وجَرّأك على عِصْيانه ؟","sorah_name" : "الإنفطار","ayah_number" : "6","kalemah_root" : "غرر","kalemah_no_tashkeel" : "غرك","kalemah_num_in_ayah" : "4","kalemat_count_in_ayah" : "6"},
{"soura_nu":"82","ref_number" : "75735","word_w_tashkeel" : "بِرَبِّكَ","kalemah_tafseer" : "بِإلَهِكَ الْمَعْبود","sorah_name" : "الإنفطار","ayah_number" : "6","kalemah_root" : "ربب","kalemah_no_tashkeel" : "بربك","kalemah_num_in_ayah" : "5","kalemat_count_in_ayah" : "6"},
{"soura_nu":"82","ref_number" : "75736","word_w_tashkeel" : "الْكَرِيمِ","kalemah_tafseer" : "هو الكثير الخير فيبدأ بالنعمة قبل الاستحقاق ويتبرع بالاحسان من غير استثابة، والكريم من أسْماءِ اللهِ الحُسْنى","sorah_name" : "الإنفطار","ayah_number" : "6","kalemah_root" : "كرم","kalemah_no_tashkeel" : "الكريم","kalemah_num_in_ayah" : "6","kalemat_count_in_ayah" : "6"},
{"soura_nu":"82","ref_number" : "75737","word_w_tashkeel" : "الَّذِي","kalemah_tafseer" : "اسْمٌ مَوْصولٌ لِلْمُفْرَدِ المُذَكَّرِ","sorah_name" : "الإنفطار","ayah_number" : "7","kalemah_root" : "الذي","kalemah_no_tashkeel" : "الذي","kalemah_num_in_ayah" : "1","kalemat_count_in_ayah" : "4"},
{"soura_nu":"82","ref_number" : "75738","word_w_tashkeel" : "خَلَقَكَ","kalemah_tafseer" : "أوْجَدَكَ عَلى غَيْرِ مِثالٍ سابِقٍ ويَكونُ خَلْقُ الله مِنَ العَدَمِ","sorah_name" : "الإنفطار","ayah_number" : "7","kalemah_root" : "خلق","kalemah_no_tashkeel" : "خلقك","kalemah_num_in_ayah" : "2","kalemat_count_in_ayah" : "4"},
{"soura_nu":"82","ref_number" : "75739","word_w_tashkeel" : "فَسَوَّاكَ","kalemah_tafseer" : "سَوَّاكَ: كَمَّلَكَ رَجُلاً مُستقِلاًّ بِأمْرِكَ وجَعَل أعْضاءَك سَويّة سليمة","sorah_name" : "الإنفطار","ayah_number" : "7","kalemah_root" : "سوي","kalemah_no_tashkeel" : "فسواك","kalemah_num_in_ayah" : "3","kalemat_count_in_ayah" : "4"},
{"soura_nu":"82","ref_number" : "75740","word_w_tashkeel" : "فَعَدَلَكَ","kalemah_tafseer" : "فَجَعَلك مُنَسَّقَ الخَلْق","sorah_name" : "الإنفطار","ayah_number" : "7","kalemah_root" : "عدل","kalemah_no_tashkeel" : "فعدلك","kalemah_num_in_ayah" : "4","kalemat_count_in_ayah" : "4"},
{"soura_nu":"82","ref_number" : "75741","word_w_tashkeel" : "فِي","kalemah_tafseer" : "حَرْفُ جَرٍّ يُفيدُ مَعْنى الظَّرْفِيَّةِ المَجازِيَّةِ","sorah_name" : "الإنفطار","ayah_number" : "8","kalemah_root" : "في","kalemah_no_tashkeel" : "في","kalemah_num_in_ayah" : "1","kalemat_count_in_ayah" : "6"},
{"soura_nu":"82","ref_number" : "75742","word_w_tashkeel" : "أَيِّ","kalemah_tafseer" : "أَيّ: اسْم اسْتِفْهامٍ أوْ كَمالِيَّة تُفيدُ المَدْحَ والتَّعَجُّبَ","sorah_name" : "الإنفطار","ayah_number" : "8","kalemah_root" : "اي","kalemah_no_tashkeel" : "أي","kalemah_num_in_ayah" : "2","kalemat_count_in_ayah" : "6"},
{"soura_nu":"82","ref_number" : "75743","word_w_tashkeel" : "صُورَةٍ","kalemah_tafseer" : "شَكْلٍ أوْ صورَةٍ مُجَسَّمَةٍ","sorah_name" : "الإنفطار","ayah_number" : "8","kalemah_root" : "صور","kalemah_no_tashkeel" : "صورة","kalemah_num_in_ayah" : "3","kalemat_count_in_ayah" : "6"},
{"soura_nu":"82","ref_number" : "75744","word_w_tashkeel" : "مَّا","kalemah_tafseer" : "مُؤَكِّدَةٌ وظيفَتُها التَّعويضُ عَن فِعلٍ مَحذوفٍ أو تأكيدُ السِّياقِ التي تَرِدُ فيهِ","sorah_name" : "الإنفطار","ayah_number" : "8","kalemah_root" : "ما","kalemah_no_tashkeel" : "ما","kalemah_num_in_ayah" : "4","kalemat_count_in_ayah" : "6"},
{"soura_nu":"82","ref_number" : "75745","word_w_tashkeel" : "شَاء","kalemah_tafseer" : "أرادَ","sorah_name" : "الإنفطار","ayah_number" : "8","kalemah_root" : "شيأ","kalemah_no_tashkeel" : "شاء","kalemah_num_in_ayah" : "5","kalemat_count_in_ayah" : "6"},
{"soura_nu":"82","ref_number" : "75746","word_w_tashkeel" : "رَكَّبَكَ","kalemah_tafseer" : "صوّرك","sorah_name" : "الإنفطار","ayah_number" : "8","kalemah_root" : "ركب","kalemah_no_tashkeel" : "ركبك","kalemah_num_in_ayah" : "6","kalemat_count_in_ayah" : "6"},
{"soura_nu":"82","ref_number" : "75747","word_w_tashkeel" : "كَلَّا","kalemah_tafseer" : "حَرْفٌ لِنَفْيِ الجَوابِ جاءَ للإسْتِفْتاحِ والتَنْبيهِ","sorah_name" : "الإنفطار","ayah_number" : "9","kalemah_root" : "كلا","kalemah_no_tashkeel" : "كلا","kalemah_num_in_ayah" : "1","kalemat_count_in_ayah" : "4"},
{"soura_nu":"82","ref_number" : "75748","word_w_tashkeel" : "بَلْ","kalemah_tafseer" : "حَرْفُ ابتِداءٍ غَيْرُ عاطِفٍ يُفيدُ مَعْنَى الإنتِقالِ أو التَّوكيدِ","sorah_name" : "الإنفطار","ayah_number" : "9","kalemah_root" : "بل","kalemah_no_tashkeel" : "بل","kalemah_num_in_ayah" : "2","kalemat_count_in_ayah" : "4"},
{"soura_nu":"82","ref_number" : "75749","word_w_tashkeel" : "تُكَذِّبُونَ","kalemah_tafseer" : "تُنْكِرون","sorah_name" : "الإنفطار","ayah_number" : "9","kalemah_root" : "كذب","kalemah_no_tashkeel" : "تكذبون","kalemah_num_in_ayah" : "3","kalemat_count_in_ayah" : "4"},
{"soura_nu":"82","ref_number" : "75750","word_w_tashkeel" : "بِالدِّينِ","kalemah_tafseer" : "بالبعث والجزاء أو بالإسلام","sorah_name" : "الإنفطار","ayah_number" : "9","kalemah_root" : "دين","kalemah_no_tashkeel" : "بالدين","kalemah_num_in_ayah" : "4","kalemat_count_in_ayah" : "4"},
{"soura_nu":"82","ref_number" : "75751","word_w_tashkeel" : "وَإِنَّ","kalemah_tafseer" : "إِنَّ: حَرْفُ تَوْكيدٍ ونَصْبٍ يُفيدُ تأكيدَ مَضْمونِ الجُملَةِ","sorah_name" : "الإنفطار","ayah_number" : "10","kalemah_root" : "ان","kalemah_no_tashkeel" : "وإن","kalemah_num_in_ayah" : "1","kalemat_count_in_ayah" : "3"},
{"soura_nu":"82","ref_number" : "75752","word_w_tashkeel" : "عَلَيْكُمْ","kalemah_tafseer" : "عَلَى: حَرْفُ جَرٍّ يُفيدُ مَعْنى الإستِعْلاءِ المَجازي","sorah_name" : "الإنفطار","ayah_number" : "10","kalemah_root" : "على","kalemah_no_tashkeel" : "عليكم","kalemah_num_in_ayah" : "2","kalemat_count_in_ayah" : "3"},
{"soura_nu":"82","ref_number" : "75753","word_w_tashkeel" : "لَحَافِظِينَ","kalemah_tafseer" : "حَافِظِينَ: ملائكة حارِسينَ مُراقِبينَ","sorah_name" : "الإنفطار","ayah_number" : "10","kalemah_root" : "حفظ","kalemah_no_tashkeel" : "لحافظين","kalemah_num_in_ayah" : "3","kalemat_count_in_ayah" : "3"},
{"soura_nu":"82","ref_number" : "75754","word_w_tashkeel" : "كِرَاماً","kalemah_tafseer" : "شُرَفاء، كراماً على الله","sorah_name" : "الإنفطار","ayah_number" : "11","kalemah_root" : "كرم","kalemah_no_tashkeel" : "كراما","kalemah_num_in_ayah" : "1","kalemat_count_in_ayah" : "2"},
{"soura_nu":"82","ref_number" : "75755","word_w_tashkeel" : "كَاتِبِينَ","kalemah_tafseer" : "مُسَجِّلين ومُدَوِّنين","sorah_name" : "الإنفطار","ayah_number" : "11","kalemah_root" : "كتب","kalemah_no_tashkeel" : "كاتبين","kalemah_num_in_ayah" : "2","kalemat_count_in_ayah" : "2"},
{"soura_nu":"82","ref_number" : "75756","word_w_tashkeel" : "يَعْلَمُونَ","kalemah_tafseer" : "يَعْرِفونَ ويُدْرِكُونَ","sorah_name" : "الإنفطار","ayah_number" : "12","kalemah_root" : "علم","kalemah_no_tashkeel" : "يعلمون","kalemah_num_in_ayah" : "1","kalemat_count_in_ayah" : "3"},
{"soura_nu":"82","ref_number" : "75757","word_w_tashkeel" : "مَا","kalemah_tafseer" : "يُحتَمَلُ أن تكونَ موصولَةً أو مَوْصوفَةً","sorah_name" : "الإنفطار","ayah_number" : "12","kalemah_root" : "ما","kalemah_no_tashkeel" : "ما","kalemah_num_in_ayah" : "2","kalemat_count_in_ayah" : "3"},
{"soura_nu":"82","ref_number" : "75758","word_w_tashkeel" : "تَفْعَلُونَ","kalemah_tafseer" : "تعملون","sorah_name" : "الإنفطار","ayah_number" : "12","kalemah_root" : "فعل","kalemah_no_tashkeel" : "تفعلون","kalemah_num_in_ayah" : "3","kalemat_count_in_ayah" : "3"},
{"soura_nu":"82","ref_number" : "75759","word_w_tashkeel" : "إِنَّ","kalemah_tafseer" : "حَرْفُ تَوْكيدٍ ونَصْبٍ يُفيدُ تأكيدَ مَضْمونِ الجُملَةِ","sorah_name" : "الإنفطار","ayah_number" : "13","kalemah_root" : "ان","kalemah_no_tashkeel" : "إن","kalemah_num_in_ayah" : "1","kalemat_count_in_ayah" : "4"},
{"soura_nu":"82","ref_number" : "75760","word_w_tashkeel" : "الْأَبْرَارَ","kalemah_tafseer" : "الأتقياء المُكثرين من طاعة الله والقيام بحقوق الله وحقوق عباده","sorah_name" : "الإنفطار","ayah_number" : "13","kalemah_root" : "برر","kalemah_no_tashkeel" : "الأبرار","kalemah_num_in_ayah" : "2","kalemat_count_in_ayah" : "4"},
{"soura_nu":"82","ref_number" : "75761","word_w_tashkeel" : "لَفِي","kalemah_tafseer" : "في: حَرْفُ جَرٍّ يُفيدُ مَعْنى الظَّرْفِيَّةِ المَجازِيَّةِ","sorah_name" : "الإنفطار","ayah_number" : "13","kalemah_root" : "في","kalemah_no_tashkeel" : "لفي","kalemah_num_in_ayah" : "3","kalemat_count_in_ayah" : "4"},
{"soura_nu":"82","ref_number" : "75762","word_w_tashkeel" : "نَعِيمٍ","kalemah_tafseer" : "النَّعيم: كُلّ ما يُستطاب ويُسْتَمتعُ به","sorah_name" : "الإنفطار","ayah_number" : "13","kalemah_root" : "نعم","kalemah_no_tashkeel" : "نعيم","kalemah_num_in_ayah" : "4","kalemat_count_in_ayah" : "4"},
{"soura_nu":"82","ref_number" : "75763","word_w_tashkeel" : "وَإِنَّ","kalemah_tafseer" : "إِنَّ: حَرْفُ تَوْكيدٍ ونَصْبٍ يُفيدُ تأكيدَ مَضْمونِ الجُملَةِ","sorah_name" : "الإنفطار","ayah_number" : "14","kalemah_root" : "ان","kalemah_no_tashkeel" : "وإن","kalemah_num_in_ayah" : "1","kalemat_count_in_ayah" : "4"},
{"soura_nu":"82","ref_number" : "75764","word_w_tashkeel" : "الْفُجَّارَ","kalemah_tafseer" : "الكُفّار غير المُكْتَرِثين بِكُفْرِهم","sorah_name" : "الإنفطار","ayah_number" : "14","kalemah_root" : "فجر","kalemah_no_tashkeel" : "الفجار","kalemah_num_in_ayah" : "2","kalemat_count_in_ayah" : "4"},
{"soura_nu":"82","ref_number" : "75765","word_w_tashkeel" : "لَفِي","kalemah_tafseer" : "في: حَرْفُ جَرٍّ يُفيدُ مَعْنى الظَّرْفِيَّةِ المَجازِيَّةِ","sorah_name" : "الإنفطار","ayah_number" : "14","kalemah_root" : "في","kalemah_no_tashkeel" : "لفي","kalemah_num_in_ayah" : "3","kalemat_count_in_ayah" : "4"},
{"soura_nu":"82","ref_number" : "75766","word_w_tashkeel" : "جَحِيمٍ","kalemah_tafseer" : "الجَحِيم: مِن أسْماءِ جَهَنَّمَ","sorah_name" : "الإنفطار","ayah_number" : "14","kalemah_root" : "جحم","kalemah_no_tashkeel" : "جحيم","kalemah_num_in_ayah" : "4","kalemat_count_in_ayah" : "4"},
{"soura_nu":"82","ref_number" : "75767","word_w_tashkeel" : "يَصْلَوْنَهَا","kalemah_tafseer" : "يصيبهم لهبها ويُـقـاسونَ حَرّها ويَحْتَرِقونَ فِيها","sorah_name" : "الإنفطار","ayah_number" : "15","kalemah_root" : "صلو","kalemah_no_tashkeel" : "يصلونها","kalemah_num_in_ayah" : "1","kalemat_count_in_ayah" : "3"},
{"soura_nu":"82","ref_number" : "75768","word_w_tashkeel" : "يَوْمَ","kalemah_tafseer" : "يَوْمُ الدِّينِ: يَوْمُ الجَزاءِ","sorah_name" : "الإنفطار","ayah_number" : "15","kalemah_root" : "يوم","kalemah_no_tashkeel" : "يوم","kalemah_num_in_ayah" : "2","kalemat_count_in_ayah" : "3"},
{"soura_nu":"82","ref_number" : "75769","word_w_tashkeel" : "الدِّينِ","kalemah_tafseer" : "الجَزاءِ","sorah_name" : "الإنفطار","ayah_number" : "15","kalemah_root" : "دين","kalemah_no_tashkeel" : "الدين","kalemah_num_in_ayah" : "3","kalemat_count_in_ayah" : "3"},
{"soura_nu":"82","ref_number" : "75770","word_w_tashkeel" : "وَمَا","kalemah_tafseer" : "ما: نافِيَةٌ تَعْمَلُ عَمَلَ ( لَيْسَ )","sorah_name" : "الإنفطار","ayah_number" : "16","kalemah_root" : "ما","kalemah_no_tashkeel" : "وما","kalemah_num_in_ayah" : "1","kalemat_count_in_ayah" : "4"},
{"soura_nu":"82","ref_number" : "75771","word_w_tashkeel" : "هُمْ","kalemah_tafseer" : "ضَميرُ الغَائِبينَ","sorah_name" : "الإنفطار","ayah_number" : "16","kalemah_root" : "هم","kalemah_no_tashkeel" : "هم","kalemah_num_in_ayah" : "2","kalemat_count_in_ayah" : "4"},
{"soura_nu":"82","ref_number" : "75772","word_w_tashkeel" : "عَنْهَا","kalemah_tafseer" : "عَنْ: حَرْفُ جَرٍّ يُفيدُ مَعْنَى المُجاوَزَةِ المَجازِيَّةِ","sorah_name" : "الإنفطار","ayah_number" : "16","kalemah_root" : "عن","kalemah_no_tashkeel" : "عنها","kalemah_num_in_ayah" : "3","kalemat_count_in_ayah" : "4"},
{"soura_nu":"82","ref_number" : "75773","word_w_tashkeel" : "بِغَائِبِينَ","kalemah_tafseer" : "مَا هُمْ عَنْهَا بِغائِبِينَ: مَا هُمْ عَنْ جَهَنَّمَ بِمبعدين لا بِخُروجٍ ولا بِمَوْتٍ","sorah_name" : "الإنفطار","ayah_number" : "16","kalemah_root" : "غيب","kalemah_no_tashkeel" : "بغائبين","kalemah_num_in_ayah" : "4","kalemat_count_in_ayah" : "4"},
{"soura_nu":"82","ref_number" : "75774","word_w_tashkeel" : "وَمَا","kalemah_tafseer" : "ما: اسمٌ يُسْتَفْهَمُ بِهِ عَنْ غيْرِ العاقِلِ وعَن حَقيقَةِ الشَّيْءِ أو صِفَتِهِ","sorah_name" : "الإنفطار","ayah_number" : "17","kalemah_root" : "ما","kalemah_no_tashkeel" : "وما","kalemah_num_in_ayah" : "1","kalemat_count_in_ayah" : "5"},
{"soura_nu":"82","ref_number" : "75775","word_w_tashkeel" : "أَدْرَاكَ","kalemah_tafseer" : "وَمَا أَدْرَاكَ: وَمَا أَعْلَمَكَ","sorah_name" : "الإنفطار","ayah_number" : "17","kalemah_root" : "دري","kalemah_no_tashkeel" : "أدراك","kalemah_num_in_ayah" : "2","kalemat_count_in_ayah" : "5"},
{"soura_nu":"82","ref_number" : "75776","word_w_tashkeel" : "مَا","kalemah_tafseer" : "اسمٌ يُسْتَفْهَمُ بِهِ عَنْ غيْرِ العاقِلِ وعَن حَقيقَةِ الشيْءِ أو صِفَتِهِ","sorah_name" : "الإنفطار","ayah_number" : "17","kalemah_root" : "ما","kalemah_no_tashkeel" : "ما","kalemah_num_in_ayah" : "3","kalemat_count_in_ayah" : "5"},
{"soura_nu":"82","ref_number" : "75777","word_w_tashkeel" : "يَوْمُ","kalemah_tafseer" : "يَوْمُ الدِّينِ: يَوْمُ الجَزاءِ","sorah_name" : "الإنفطار","ayah_number" : "17","kalemah_root" : "يوم","kalemah_no_tashkeel" : "يوم","kalemah_num_in_ayah" : "4","kalemat_count_in_ayah" : "5"},
{"soura_nu":"82","ref_number" : "75778","word_w_tashkeel" : "الدِّينِ","kalemah_tafseer" : "الجَزاءِ","sorah_name" : "الإنفطار","ayah_number" : "17","kalemah_root" : "دين","kalemah_no_tashkeel" : "الدين","kalemah_num_in_ayah" : "5","kalemat_count_in_ayah" : "5"},
{"soura_nu":"82","ref_number" : "75779","word_w_tashkeel" : "ثُمَّ","kalemah_tafseer" : "حَرْفُ عَطْفٍ يُفيدُ مَعْنى التَّوْكيدِ","sorah_name" : "الإنفطار","ayah_number" : "18","kalemah_root" : "ثم","kalemah_no_tashkeel" : "ثم","kalemah_num_in_ayah" : "1","kalemat_count_in_ayah" : "6"},
{"soura_nu":"82","ref_number" : "75780","word_w_tashkeel" : "مَا","kalemah_tafseer" : "اسمٌ يُسْتَفْهَمُ بِهِ عَنْ غيْرِ العاقِلِ وعَن حَقيقَةِ الشيْءِ أو صِفَتِهِ","sorah_name" : "الإنفطار","ayah_number" : "18","kalemah_root" : "ما","kalemah_no_tashkeel" : "ما","kalemah_num_in_ayah" : "2","kalemat_count_in_ayah" : "6"},
{"soura_nu":"82","ref_number" : "75781","word_w_tashkeel" : "أَدْرَاكَ","kalemah_tafseer" : "مَا أَدْرَاكَ: مَا أَعْلَمَكَ","sorah_name" : "الإنفطار","ayah_number" : "18","kalemah_root" : "دري","kalemah_no_tashkeel" : "أدراك","kalemah_num_in_ayah" : "3","kalemat_count_in_ayah" : "6"},
{"soura_nu":"82","ref_number" : "75782","word_w_tashkeel" : "مَا","kalemah_tafseer" : "اسمٌ يُسْتَفْهَمُ بِهِ عَنْ غيْرِ العاقِلِ وعَن حَقيقَةِ الشيْءِ أو صِفَتِهِ","sorah_name" : "الإنفطار","ayah_number" : "18","kalemah_root" : "ما","kalemah_no_tashkeel" : "ما","kalemah_num_in_ayah" : "4","kalemat_count_in_ayah" : "6"},
{"soura_nu":"82","ref_number" : "75783","word_w_tashkeel" : "يَوْمُ","kalemah_tafseer" : "يَوْمُ الدِّينِ: يَوْمُ الجَزاءِ","sorah_name" : "الإنفطار","ayah_number" : "18","kalemah_root" : "يوم","kalemah_no_tashkeel" : "يوم","kalemah_num_in_ayah" : "5","kalemat_count_in_ayah" : "6"},
{"soura_nu":"82","ref_number" : "75784","word_w_tashkeel" : "الدِّينِ","kalemah_tafseer" : "الجَزاءِ","sorah_name" : "الإنفطار","ayah_number" : "18","kalemah_root" : "دين","kalemah_no_tashkeel" : "الدين","kalemah_num_in_ayah" : "6","kalemat_count_in_ayah" : "6"},
{"soura_nu":"82","ref_number" : "75785","word_w_tashkeel" : "يَوْمَ","kalemah_tafseer" : "المراد يوم القيامة","sorah_name" : "الإنفطار","ayah_number" : "19","kalemah_root" : "يوم","kalemah_no_tashkeel" : "يوم","kalemah_num_in_ayah" : "1","kalemat_count_in_ayah" : "9"},
{"soura_nu":"82","ref_number" : "75786","word_w_tashkeel" : "لا","kalemah_tafseer" : "نافِيَةٌ غَيْرُ عامِلَةٍ","sorah_name" : "الإنفطار","ayah_number" : "19","kalemah_root" : "لا","kalemah_no_tashkeel" : "لا","kalemah_num_in_ayah" : "2","kalemat_count_in_ayah" : "9"},
{"soura_nu":"82","ref_number" : "75787","word_w_tashkeel" : "تَمْلِكُ","kalemah_tafseer" : "لا تَمْلِك: لا تستطيع","sorah_name" : "الإنفطار","ayah_number" : "19","kalemah_root" : "ملك","kalemah_no_tashkeel" : "تملك","kalemah_num_in_ayah" : "3","kalemat_count_in_ayah" : "9"},
{"soura_nu":"82","ref_number" : "75788","word_w_tashkeel" : "نَفْسٌ","kalemah_tafseer" : "النفس : الذات أي الروح والجسم معا","sorah_name" : "الإنفطار","ayah_number" : "19","kalemah_root" : "نفس","kalemah_no_tashkeel" : "نفس","kalemah_num_in_ayah" : "4","kalemat_count_in_ayah" : "9"},
{"soura_nu":"82","ref_number" : "75789","word_w_tashkeel" : "لِّنَفْسٍ","kalemah_tafseer" : "النفس : الذات أي الروح والجسم معا","sorah_name" : "الإنفطار","ayah_number" : "19","kalemah_root" : "نفس","kalemah_no_tashkeel" : "لنفس","kalemah_num_in_ayah" : "5","kalemat_count_in_ayah" : "9"},
{"soura_nu":"82","ref_number" : "75790","word_w_tashkeel" : "شَيْئاً","kalemah_tafseer" : "الشَّيْءُ: ما يَصِحُّ أنْ يُخْبَرَ عَنْهُ حِسِّيّاً كانَ أوْ مَعْنَوِيّاً","sorah_name" : "الإنفطار","ayah_number" : "19","kalemah_root" : "شيأ","kalemah_no_tashkeel" : "شيئا","kalemah_num_in_ayah" : "6","kalemat_count_in_ayah" : "9"},
{"soura_nu":"82","ref_number" : "75791","word_w_tashkeel" : "وَالْأَمْرُ","kalemah_tafseer" : "والحُكْمُ والقضاءُ","sorah_name" : "الإنفطار","ayah_number" : "19","kalemah_root" : "أمر","kalemah_no_tashkeel" : "والأمر","kalemah_num_in_ayah" : "7","kalemat_count_in_ayah" : "9"},
{"soura_nu":"82","ref_number" : "75792","word_w_tashkeel" : "يَوْمَئِذٍ","kalemah_tafseer" : "ذَلِكَ اليَوْم","sorah_name" : "الإنفطار","ayah_number" : "19","kalemah_root" : "يوم","kalemah_no_tashkeel" : "يومئذ","kalemah_num_in_ayah" : "8","kalemat_count_in_ayah" : "9"},
{"soura_nu":"82","ref_number" : "75793","word_w_tashkeel" : "لِلَّهِ","kalemah_tafseer" : "اللهُ: اسْمٌ لِلذَّاتِ العَلِيَّةِ المُتَفَرِّدَةِ بالألوهِيَّةِ الواجِبَةِ الوُجودِ المَعبودَةِ بِحَقٍّ، وهوَ لَفظُ الجَلالَةِ الجامِعُ لِمَعاني صِفاتِ اللهِ الكامِلة","sorah_name" : "الإنفطار","ayah_number" : "19","kalemah_root" : "أله","kalemah_no_tashkeel" : "لله","kalemah_num_in_ayah" : "9","kalemat_count_in_ayah" : "9"}
]